{
  "url": "https://etherscan.io/address/0xC874b064f465bdD6411D45734b56fac750Cda29A",
  "host": "etherscan.io",
  "address": "0xC874b064f465bdD6411D45734b56fac750Cda29A",
  "chainid": 1,
  "project_slug": "stakewise",
  "asset_id": "7dvyIqMe1AnZBftHYD8yUx",
  "contract_name": "AdminUpgradeabilityProxy",
  "compiler_version": "v0.6.8+commit.0bbfe453",
  "optimization_used": "0",
  "runs": "200",
  "constructor_arguments": "",
  "evm_version": "Default",
  "library": "",
  "license_type": "",
  "proxy": "1",
  "implementation": "0x481f28c0d733614af87897e43d0d52c451799592",
  "swarm_source": "",
  "fetch_messages": [
    "etherscan-v2:ok"
  ],
  "files_written": 4,
  "mode": "json-sources"
}
