{
  "url": "https://etherscan.io/address/0x9751572B505F244D9feCfcB9712B00974f458872#code",
  "host": "etherscan.io",
  "address": "0x9751572B505F244D9feCfcB9712B00974f458872",
  "chainid": 1,
  "project_slug": "daimo-pay",
  "asset_id": "ks4fMgIqqBXwlnrgpc1rq",
  "contract_name": "PayIntentFactory",
  "compiler_version": "v0.8.26+commit.8a97fa7a",
  "optimization_used": "1",
  "runs": "999999",
  "constructor_arguments": "",
  "evm_version": "london",
  "library": "",
  "license_type": "",
  "proxy": "0",
  "implementation": "",
  "swarm_source": "",
  "fetch_messages": [
    "etherscan-v2:ok"
  ],
  "files_written": 22,
  "mode": "json-sources"
}
