{
  "url": "https://etherscan.io/address/0x2fe16Dd18bba26e457B7dD2080d5674312b026a2",
  "host": "etherscan.io",
  "address": "0x2fe16Dd18bba26e457B7dD2080d5674312b026a2",
  "chainid": 1,
  "project_slug": "integral",
  "asset_id": "7dA7nLFsFs0gRXmoSLnHX3",
  "contract_name": "TwapPair",
  "compiler_version": "v0.7.6+commit.7338295f",
  "optimization_used": "1",
  "runs": "200",
  "constructor_arguments": "",
  "evm_version": "Default",
  "library": "",
  "license_type": "",
  "proxy": "0",
  "implementation": "",
  "swarm_source": "",
  "fetch_messages": [
    "etherscan-v2:ok"
  ],
  "files_written": 12,
  "mode": "json-sources"
}
