{
  "url": "https://etherscan.io/address/0xd042C267758eDDf34B481E1F539d637e41db3e5a",
  "host": "etherscan.io",
  "address": "0xd042C267758eDDf34B481E1F539d637e41db3e5a",
  "chainid": 1,
  "project_slug": "audit-comp-anvil",
  "asset_id": "4ywmkFrGN0DbBu2QrknIoS",
  "contract_name": "TimeBasedCollateralPool",
  "compiler_version": "v0.8.25+commit.b61c2a91",
  "optimization_used": "1",
  "runs": "999999",
  "constructor_arguments": "",
  "evm_version": "paris",
  "library": "",
  "license_type": "",
  "proxy": "0",
  "implementation": "",
  "swarm_source": "",
  "fetch_messages": [
    "etherscan-v2:ok"
  ],
  "files_written": 15,
  "mode": "json-sources"
}
